src/__init__.py
src/color_logger.py
src/config_loader.py
src/exchange_binance.py
src/exchange_factory.py
src/exchange_ws.py
src/exchanges_ws.py
src/helpers.py
src/modules_version.py
src/rabbitmq_communicator.py
src/rabbitmq_service.py
src/web_service.py
atb_lib-0.7.4.dist-info/METADATA
atb_lib-0.7.4.dist-info/WHEEL
atb_lib-0.7.4.dist-info/RECORD
