Metadata-Version: 2.1
Name: atb-lib
Version: 0.7.4
Summary: A Python package for Advanced Trading Bot
License: MIT
Author: Yuriy Tigiev
Author-email: yuriy.tigiev@outlook.com
Requires-Python: >=3.12,<4.0
Classifier: License :: OSI Approved :: MIT License
Classifier: Programming Language :: Python :: 3
Classifier: Programming Language :: Python :: 3.12
Requires-Dist: aio-pika (>=9.4.0,<10.0.0)
Requires-Dist: arrow (>=1.3.0,<2.0.0)
Requires-Dist: asyncio (>=3.4.3,<4.0.0)
Requires-Dist: colorlog (>=6.8.2,<7.0.0)
Requires-Dist: fastapi (>=0.109.2,<0.110.0)
Requires-Dist: importlib-metadata (>=7.0.1,<8.0.0)
Requires-Dist: msgpack (>=1.0.7,<2.0.0)
Requires-Dist: pip (>=24.0.0,<25.0.0)
Requires-Dist: ujson (>=5.9.0,<6.0.0)
Requires-Dist: uvicorn (>=0.27.1,<0.28.0)
Requires-Dist: websockets (>=12.0,<13.0)
Requires-Dist: wheel (>=0.42.0,<0.43.0)
